bewe/__init__.py
bewe/alpha_seeker/__init__.py
bewe/alpha_seeker/base_data.py
bewe/alpha_seeker/base_data_test.py
bewe/alpha_seeker/base_strategy.py
bewe/alpha_seeker/daily_stock_loader.py
bewe/backtest/__init__.py
bewe/backtest/backtester.py
bewe/backtest/backtester_test.py
bewe/backtest/holder.py
bewe/backtest/holder_test.py
bewe/services/__init__.py
bewe/services/entrypoint.py
bewe/services/modes.py
bewe/services/crawler/__init__.py
bewe/services/crawler/finmind_downloader.py
bewe/services/crawler/secret_manager.py
bewe/services/databases/__init__.py
bewe/services/databases/asset_orm.py
bewe/services/databases/db_manager.py
bewe-0.1.3.1693408019.dist-info/METADATA
bewe-0.1.3.1693408019.dist-info/WHEEL
bewe-0.1.3.1693408019.dist-info/top_level.txt
bewe-0.1.3.1693408019.dist-info/RECORD
