Metadata-Version: 2.1
Name: bewe
Version: 0.1.3.1693408019
Summary: The package implements some investment strategies.
Author: Berlin Hsin
Author-email: berlin.hsin@gmail.com
